[1,["47/0i9dI1MNanzjD15q1n8@6c48a"],["_textureSource"],["cc.SpriteFrame"],0,[{"name":"talk10","rect":{"x":1,"y":1,"width":625,"height":202},"offset":{"x":0.5,"y":-0.5},"originalSize":{"width":626,"height":203},"rotated":false,"capInsets":[0,0,0,0],"vertices":{"rawPosition":[-312.5,-101,0,312.5,-101,0,-312.5,101,0,312.5,101,0],"indexes":[0,1,2,2,1,3],"uv":[1,202,626,202,1,0,626,0],"nuv":[0.001597444089456869,0,1,0,0.001597444089456869,0.9950738916256158,1,0.9950738916256158],"minPos":{"x":-312.5,"y":-101,"z":0},"maxPos":{"x":312.5,"y":101,"z":0}},"packable":true,"pixelsToUnit":100,"pivot":{"x":0.5,"y":0.5},"meshType":0}],[0],0,[0],[0],[0]]
